{
  "part1": [
    {
      "No. in Season": 1,
      "No. in Part": 1,
      "Title": "We're Back in Tokyo",
      "Netflix Japan Release Date": "May 14, 2019",
      "Fuji TV Air Date": "TBA",
      "Length (mins)": 40
    },
    {
      "No. in Season": 2,
      "No. in Part": 2,
      "Title": "Tempura Incident",
      "Netflix Japan Release Date": "May 21, 2019",
      "Fuji TV Air Date": "TBA",
      "Length (mins)": 39
    },
    {
      "No. in Season": 3,
      "No. in Part": 3,
      "Title": "Dreamed of Her",
      "Netflix Japan Release Date": "May 28, 2019",
      "Fuji TV Air Date": "TBA",
      "Length (mins)": 37
    },
    {
      "No. in Season": 4,
      "No. in Part": 4,
      "Title": "I Want to Be a Hero",
      "Netflix Japan Release Date": "June 4, 2019",
      "Fuji TV Air Date": "TBA",
      "Length (mins)": 42
    },
    {
      "No. in Season": 5,
      "No. in Part": 5,
      "Title": "Reiwa!!",
      "Netflix Japan Release Date": "June 18, 2019",
      "Fuji TV Air Date": "TBA",
      "Length (mins)": 45
    },
    {
      "No. in Season": 6,
      "No. in Part": 6,
      "Title": "The Grass is Greener on the Other Side",
      "Netflix Japan Release Date": "June 25, 2019",
      "Fuji TV Air Date": "TBA",
      "Length (mins)": 57
    },
    {
      "No. in Season": 7,
      "No. in Part": 7,
      "Title": "Woman to Treat and Woman to Split the Check",
      "Netflix Japan Release Date": "July 2, 2019",
      "Fuji TV Air Date": "TBA",
      "Length (mins)": 45
    },
    {
      "No. in Season": 8,
      "No. in Part": 8,
      "Title": "Passive Boys",
      "Netflix Japan Release Date": "July 9, 2019",
      "Fuji TV Air Date": "TBA",
      "Length (mins)": 48
    },
    {
      "No. in Season": 9,
      "No. in Part": 9,
      "Title": "Girlfight",
      "Netflix Japan Release Date": "July 23, 2019",
      "Fuji TV Air Date": "TBA",
      "Length (mins)": 45
    },
    {
      "No. in Season": 10,
      "No. in Part": 10,
      "Title": "The Boy That Gets Treated",
      "Netflix Japan Release Date": "July 30, 2019",
      "Fuji TV Air Date": "TBA",
      "Length (mins)": 43
    },
    {
      "No. in Season": 11,
      "No. in Part": 11,
      "Title": "Broccoli Pasta, Carbonara-Style",
      "Netflix Japan Release Date": "August 6, 2019",
      "Fuji TV Air Date": "TBA",
      "Length (mins)": 49
    },
    {
      "No. in Season": 12,
      "No. in Part": 12,
      "Title": "Always Chillin'",
      "Netflix Japan Release Date": "August 13, 2019",
      "Fuji TV Air Date": "TBA",
      "Length (mins)": 46
    }
  ],
  "part2": [
    {
      "No. in Season": 13,
      "No. in Part": 1,
      "Title": "All Or Nothing",
      "Netflix Japan Release Date": "August 27, 2019",
      "Fuji TV Air Date": "TBA",
      "Length (mins)": 48
    },
    {
      "No. in Season": 14,
      "No. in Part": 2,
      "Title": "Just A Moment, Please",
      "Netflix Japan Release Date": "September 3, 2019",
      "Fuji TV Air Date": "TBA",
      "Length (mins)": 43
    },
    {
      "No. in Season": 15,
      "No. in Part": 3,
      "Title": "A Man's Worth Is Determined By His Job",
      "Netflix Japan Release Date": "September 10, 2019",
      "Fuji TV Air Date": "TBA",
      "Length (mins)": 38
    },
    {
      "No. in Season": 16,
      "No. in Part": 4,
      "Title": "Orange Flavor First Kiss",
      "Netflix Japan Release Date": "September 17, 2019",
      "Fuji TV Air Date": "TBA",
      "Length (mins)": 44
    },
    {
      "No. in Season": 17,
      "No. in Part": 5,
      "Title": "This is Not a Place to Slack",
      "Netflix Japan Release Date": "October 1, 2019",
      "Fuji TV Air Date": "TBA",
      "Length (mins)": 37
    },
    {
      "No. in Season": 18,
      "No. in Part": 6,
      "Title": "Bros Before Hoes",
      "Netflix Japan Release Date": "October 8, 2019",
      "Fuji TV Air Date": "TBA",
      "Length (mins)": 35
    },
    {
      "No. in Season": 19,
      "No. in Part": 7,
      "Title": "The Stray Sheep",
      "Netflix Japan Release Date": "October 15, 2019",
      "Fuji TV Air Date": "TBA",
      "Length (mins)": 38
    },
    {
      "No. in Season": 20,
      "No. in Part": 8,
      "Title": "The Third Flower",
      "Netflix Japan Release Date": "October 22, 2019",
      "Fuji TV Air Date": "TBA",
      "Length (mins)": 41
    },
    {
      "No. in Season": 21,
      "No. in Part": 9,
      "Title": "Too Shy Girl",
      "Netflix Japan Release Date": "November 5, 2019",
      "Fuji TV Air Date": "TBA",
      "Length (mins)": 43
    },
    {
      "No. in Season": 22,
      "No. in Part": 10,
      "Title": "Tip Off",
      "Netflix Japan Release Date": "November 12, 2019",
      "Fuji TV Air Date": "TBA",
      "Length (mins)": 44
    },
    {
      "No. in Season": 23,
      "No. in Part": 11,
      "Title": "Friendship Between Men and Women",
      "Netflix Japan Release Date": "November 19, 2019",
      "Fuji TV Air Date": "TBA",
      "Length (mins)": 44
    },
    {
      "No. in Season": 24,
      "No. in Part": 12,
      "Title": "Pink Rose",
      "Netflix Japan Release Date": "November 26, 2019",
      "Fuji TV Air Date": "TBA",
      "Length (mins)": 40
    }
  ],
  "part3": [
    {
      "No. in Season": 25,
      "No. in Part": 1,
      "Title": "The Girls Can't Do It",
      "Netflix Japan Release Date": "December 9, 2019",
      "Fuji TV Air Date": "TBA",
      "Length (mins)": 52
    },
    {
      "No. in Season": 26,
      "No. in Part": 2,
      "Title": "Internationalization at Once",
      "Netflix Japan Release Date": "December 16, 2019",
      "Fuji TV Air Date": "TBA",
      "Length (mins)": 41
    },
    {
      "No. in Season": 27,
      "No. in Part": 3,
      "Title": "I Can't Be Here",
      "Netflix Japan Release Date": "December 24, 2019",
      "Fuji TV Air Date": "TBA",
      "Length (mins)": 38
    },
    {
      "No. in Season": 28,
      "No. in Part": 4,
      "Title": "Starving for Affection",
      "Netflix Japan Release Date": "December 31, 2019",
      "Fuji TV Air Date": "TBA",
      "Length (mins)": 47
    },
    {
      "No. in Season": 29,
      "No. in Part": 5,
      "Title": "About Love",
      "Netflix Japan Release Date": "January 14, 2020",
      "Fuji TV Air Date": "TBA",
      "Length (mins)": 50
    },
    {
      "No. in Season": 30,
      "No. in Part": 6,
      "Title": "Not Guilty",
      "Netflix Japan Release Date": "January 21, 2020",
      "Fuji TV Air Date": "TBA",
      "Length (mins)": 47
    },
    {
      "No. in Season": 31,
      "No. in Part": 7,
      "Title": "Publicity Stunt",
      "Netflix Japan Release Date": "January 28, 2020",
      "Fuji TV Air Date": "TBA",
      "Length (mins)": 40
    },
    {
      "No. in Season": 32,
      "No. in Part": 8,
      "Title": "I Hate You",
      "Netflix Japan Release Date": "February 4, 2020",
      "Fuji TV Air Date": "TBA",
      "Length (mins)": 40
    },
    {
      "No. in Season": 33,
      "No. in Part": 9,
      "Title": "Half Blue",
      "Netflix Japan Release Date": "February 18, 2020",
      "Fuji TV Air Date": "TBA",
      "Length (mins)": 44
    },
    {
      "No. in Season": 34,
      "No. in Part": 10,
      "Title": "Case of The Bottle Beer Incident",
      "Netflix Japan Release Date": "February 25, 2020",
      "Fuji TV Air Date": "TBA",
      "Length (mins)": 46
    },
    {
      "No. in Season": 35,
      "No. in Part": 11,
      "Title": "The Monster in the Hallway",
      "Netflix Japan Release Date": "March 3, 2020",
      "Fuji TV Air Date": "TBA",
      "Length (mins)": 45
    },
    {
      "No. in Season": 36,
      "No. in Part": 12,
      "Title": "Angel",
      "Netflix Japan Release Date": "March 10, 2020",
      "Fuji TV Air Date": "TBA",
      "Length (mins)": 48
    }
  ],
  "part4": [
    {
      "No. in Season": 37,
      "No. in Part": 1,
      "Title": "Another Terrace!!",
      "Netflix Japan Release Date": "March 24, 2020",
      "Fuji TV Air Date": "TBA",
      "Length (mins)": 48
    },
    {
      "No. in Season": 38,
      "No. in Part": 2,
      "Title": "Case of The Costume Incident",
      "Netflix Japan Release Date": "March 31, 2020",
      "Fuji TV Air Date": "TBA",
      "Length (mins)": 42
    },
    {
      "No. in Season": 39,
      "No. in Part": 3,
      "Title": "Always Remembered",
      "Netflix Japan Release Date": "April 7, 2020",
      "Fuji TV Air Date": "TBA",
      "Length (mins)": 46
    },
    {
      "No. in Season": 40,
      "No. in Part": 4,
      "Title": "Never Forgive Luigi",
      "Netflix Japan Release Date": "April 14, 2020",
      "Fuji TV Air Date": "TBA",
      "Length (mins)": 44
    },
    {
      "No. in Season": 41,
      "No. in Part": 5,
      "Title": "Life-Threatening Date",
      "Netflix Japan Release Date": "May 12, 2020",
      "Fuji TV Air Date": "TBA",
      "Length (mins)": 42
    },
    {
      "No. in Season": 42,
      "No. in Part": 6,
      "Title": "Woman Who Makes Everyone Dream",
      "Netflix Japan Release Date": "May 19, 2020",
      "Fuji TV Air Date": "TBA",
      "Length (mins)": 43
    }
  ]
}